dagster_pyspark/__init__.py
dagster_pyspark/resources.py
dagster_pyspark/types.py
dagster_pyspark/utils.py
dagster_pyspark/version.py
dagster_pyspark-1.0.5.dist-info/LICENSE
dagster_pyspark-1.0.5.dist-info/METADATA
dagster_pyspark-1.0.5.dist-info/WHEEL
dagster_pyspark-1.0.5.dist-info/top_level.txt
dagster_pyspark-1.0.5.dist-info/RECORD
