Metadata-Version: 2.1
Name: dagster-pyspark
Version: 1.0.5
Summary: Package for PySpark Dagster framework components.
Home-page: https://github.com/dagster-io/dagster/tree/master/python_modules/dagster-framework/pyspark
Author: Elementl
Author-email: hello@elementl.com
License: Apache-2.0
Platform: UNKNOWN
Classifier: Programming Language :: Python :: 3.7
Classifier: Programming Language :: Python :: 3.8
Classifier: Programming Language :: Python :: 3.9
Classifier: Programming Language :: Python :: 3.10
Classifier: License :: OSI Approved :: Apache Software License
Classifier: Operating System :: OS Independent
License-File: LICENSE
Requires-Dist: dagster (==1.0.5)
Requires-Dist: dagster-spark (==1.0.5)
Requires-Dist: pyspark (>=2.0.2) ; python_version < "3.8"
Requires-Dist: pyspark (>=3.0.0) ; python_version >= "3.8"
